upsonic/__init__.py
upsonic/_griffe.py
upsonic/_json_schema.py
upsonic/_output.py
upsonic/_parts_manager.py
upsonic/_utils.py
upsonic/direct.py
upsonic/exceptions.py
upsonic/output.py
upsonic/py.typed
upsonic/usage.py
upsonic/agent/__init__.py
upsonic/agent/agent.py
upsonic/agent/base.py
upsonic/agent/events.py
upsonic/agent/policy_manager.py
upsonic/agent/tool_policy_manager.py
upsonic/agent/context_managers/__init__.py
upsonic/agent/context_managers/call_manager.py
upsonic/agent/context_managers/context_manager.py
upsonic/agent/context_managers/llm_manager.py
upsonic/agent/context_managers/memory_manager.py
upsonic/agent/context_managers/reliability_manager.py
upsonic/agent/context_managers/system_prompt_manager.py
upsonic/agent/context_managers/task_manager.py
upsonic/agent/deepagent/__init__.py
upsonic/agent/deepagent/constants.py
upsonic/agent/deepagent/deepagent.py
upsonic/agent/deepagent/backends/__init__.py
upsonic/agent/deepagent/backends/composite_backend.py
upsonic/agent/deepagent/backends/memory_backend.py
upsonic/agent/deepagent/backends/protocol.py
upsonic/agent/deepagent/backends/state_backend.py
upsonic/agent/deepagent/tools/__init__.py
upsonic/agent/deepagent/tools/filesystem_toolkit.py
upsonic/agent/deepagent/tools/planning_toolkit.py
upsonic/agent/deepagent/tools/subagent_toolkit.py
upsonic/agent/pipeline/__init__.py
upsonic/agent/pipeline/manager.py
upsonic/agent/pipeline/step.py
upsonic/agent/pipeline/steps.py
upsonic/cache/__init__.py
upsonic/cache/cache_manager.py
upsonic/canvas/__init__.py
upsonic/canvas/canvas.py
upsonic/chat/__init__.py
upsonic/chat/chat.py
upsonic/chat/cost_calculator.py
upsonic/chat/message.py
upsonic/chat/session_manager.py
upsonic/cli/__init__.py
upsonic/cli/main.py
upsonic/cli/printer.py
upsonic/cli/commands/__init__.py
upsonic/cli/commands/add/__init__.py
upsonic/cli/commands/add/command.py
upsonic/cli/commands/init/__init__.py
upsonic/cli/commands/init/command.py
upsonic/cli/commands/install/__init__.py
upsonic-0.71.4.dist-info/METADATA
upsonic-0.71.4.dist-info/WHEEL
upsonic-0.71.4.dist-info/entry_points.txt
upsonic-0.71.4.dist-info/licenses/LICENCE
upsonic-0.71.4.dist-info/RECORD
